property_accessor.py
property_accessor-0.1.0.dist-info/LICENSE
property_accessor-0.1.0.dist-info/WHEEL
property_accessor-0.1.0.dist-info/METADATA
property_accessor-0.1.0.dist-info/RECORD
