Metadata-Version: 2.1
Name: property-accessor
Version: 0.1.0
Summary: 
License: MIT
Author: Elielton Kremer
Author-email: elieltonkremer2392@gmail.com
Requires-Python: >=3.10,<4.0
Classifier: License :: OSI Approved :: MIT License
Classifier: Programming Language :: Python :: 3
Classifier: Programming Language :: Python :: 3.10
